bytedance_vgfm_face_processor/__init__.py
bytedance_vgfm_face_processor-0.0.1.dist-info/METADATA
bytedance_vgfm_face_processor-0.0.1.dist-info/WHEEL
bytedance_vgfm_face_processor-0.0.1.dist-info/top_level.txt
bytedance_vgfm_face_processor-0.0.1.dist-info/RECORD
