Metadata-Version: 2.1
Name: bytedance-vgfm-face-processor
Version: 0.0.1
Summary: A simple package named bytedance_vgfm_face_processor
Home-page: https://github.com/artifact/bytedance_vgfm_face_processor.git
Author: artifact
Author-email: artifact@example.com
License: UNKNOWN
Platform: UNKNOWN
Classifier: Programming Language :: Python :: 3
Classifier: License :: OSI Approved :: MIT License
Classifier: Operating System :: OS Independent
